AUTHORS
BUGS.md
CHANGES.rst
LICENSE
MANIFEST.in
README.rst
TODO.md
setup.py
sportmg/__init__.py
sportmg.egg-info/PKG-INFO
sportmg.egg-info/SOURCES.txt
sportmg.egg-info/dependency_links.txt
sportmg.egg-info/entry_points.txt
sportmg.egg-info/requires.txt
sportmg.egg-info/top_level.txt
sportmg/qt/__init__.py
sportmg/qt/main.py
sportmg/qt/widgets/__init__.py
sportmg/qt/widgets/mainwindow.py
sportmg/qt/widgets/tabs/__init__.py
sportmg/qt/widgets/tabs/bodybuilding.py
sportmg/qt/widgets/tabs/running.py
sportmg/qt/widgets/tabs/swimming.py