Metadata-Version: 1.2
Name: sportmg
Version: 1.0.dev1
Summary: A tool to manage sports sessions
Home-page: https://github.com/jeremiedecock/sportmg
Author: Jeremie DECOCK
Author-email: jd.jdhp@gmail.com
Maintainer: Jeremie DECOCK
Maintainer-email: jd.jdhp@gmail.com
License: UNKNOWN
Download-URL: https://github.com/jeremiedecock/sportmg
Keywords: sport manager
Platform: UNKNOWN
Classifier: Development Status :: 4 - Beta
Classifier: License :: OSI Approved :: MIT License
Classifier: Natural Language :: English
Classifier: Operating System :: OS Independent
Classifier: Programming Language :: Python :: 3
Classifier: Topic :: Documentation
